Adder/fullAdder.v
module fullAdder(
  input X1, X2, Cin,
  output S, Cout
);
    wire a1, a2, a3;
    xor u1(a1,X1,X2);
    and u2(a2,X1,X2);
    and u3(a3,a1,Cin);
    or u4(Cout,a2,a3);
    xor u5(S,a1,Cin);
endmodule

Adder/fullAdder_tb.v
`timescale 1ns/100ps
`include "fullAdder.v"

module fullAdder_tb();
reg A,B,Cin;
wire S,Cout;
fullAdder structural_adder(
    .X1(A),
    .X2(B),
    .Cin(Cin),
    .S(S),
    .Cout(Cout)
  );
initial begin
$dumpfile("fullAdder.vcd");
$dumpvars(0, fullAdder_tb);
A = 0;
B = 0;
Cin = 0;
#10;
A = 0;
B = 0;
Cin = 1;
#10;
A = 0;
B = 1;
Cin = 0;
#10;
A = 0;
B = 1;
Cin = 1;
#10;
A = 1;
B = 0;
Cin = 0;
#10;
A = 1;
B = 0;
Cin = 1;
#10;
A = 1;
B = 1;
Cin = 0;
#10;
A = 1;
B = 1;
Cin = 1;
#10;
  end

endmodule

Adder/fullAdder.vcd
$date
	Tue Feb 06 14:07:16 2018
$end
$version
	Icarus Verilog
$end
$timescale
	100ps
$end
$scope module fullAdder_tb $end
$var wire 1 ! S $end
$var wire 1 " Cout $end
$var reg 1 # A $end
$var reg 1 $ B $end
$var reg 1 % Cin $end
$scope module structural_adder $end
$var wire 1 % Cin $end
$var wire 1 " Cout $end
$var wire 1 ! S $end
$var wire 1 # X1 $end
$var wire 1 $ X2 $end
$var wire 1 & a1 $end
$var wire 1 ' a2 $end
$var wire 1 ( a3 $end
$upscope $end
$upscope $end
$enddefinitions $end
#0
$dumpvars
0(
0'
0&
0%
0$
0#
0"
0!
$end
#100
1!
1%
#200
1&
0%
1$
#300
1"
1(
0!
1%
#400
0"
0(
1!
0%
0$
1#
#500
1"
1(
0!
1%
#600
0(
0&
1'
0%
1$
#700
1!
1%
